elog/__init__.py
elog/logbook.py
elog/logbook_exceptions.py
py_elog-1.3.16.dist-info/LICENSE.txt
py_elog-1.3.16.dist-info/METADATA
py_elog-1.3.16.dist-info/WHEEL
py_elog-1.3.16.dist-info/top_level.txt
py_elog-1.3.16.dist-info/RECORD
