Metadata-Version: 2.1
Name: py-elog
Version: 1.3.16
Summary: Python library to access Elog.
Home-page: https://github.com/paulscherrerinstitute/py_elog
Author: Paul Scherrer Institute (PSI)
Keywords: elog,electronic,logbook
License-File: LICENSE.txt
Requires-Dist: requests
Requires-Dist: passlib
Requires-Dist: lxml
